easyascii.py
easyascii_py-1.4.0.dist-info/METADATA
easyascii_py-1.4.0.dist-info/WHEEL
easyascii_py-1.4.0.dist-info/top_level.txt
easyascii_py-1.4.0.dist-info/RECORD
