Metadata-Version: 2.4
Name: easyascii-py
Version: 1.4.0
Summary: A simple, zero-dependency library for creating ASCII art and console UIs.
Home-page: https://github.com/Matt-The-Generico/easyascii
Author: Matttz
Author-email: proactivestudiocomercial@gmail.com
Classifier: Programming Language :: Python :: 3
Classifier: License :: OSI Approved :: MIT License
Classifier: Operating System :: OS Independent
Classifier: Topic :: Terminals
Classifier: Topic :: Text Processing :: General
Requires-Python: >=3.6
Dynamic: author
Dynamic: author-email
Dynamic: classifier
Dynamic: description
Dynamic: description-content-type
Dynamic: home-page
Dynamic: requires-python
Dynamic: summary
